palinuro/__init__.py
palinuro/performance.py
palinuro_lib-0.6.dist-info/METADATA
palinuro_lib-0.6.dist-info/WHEEL
palinuro_lib-0.6.dist-info/top_level.txt
palinuro_lib-0.6.dist-info/RECORD
